{"errors":[],"warnings":[],"namedChunkGroups":{"app":{"chunks":[3,1,2,0],"assets":["webpack-runtime-e54b03d4753e5c3fd11f.js","webpack-runtime-e54b03d4753e5c3fd11f.js.map","commons-811063c764ce48470d97.js","commons-811063c764ce48470d97.js.map","styles.56c03e9eefc5b509dfdc.css","styles-57426c4aa88004c8f7a1.js","styles-57426c4aa88004c8f7a1.js.map","app-1903c4c28ed1d0f1ff3b.js","app-1903c4c28ed1d0f1ff3b.js.map"],"children":{},"childAssets":{}},"component---src-templates-docs-js":{"chunks":[],"assets":[],"children":{},"childAssets":{}}},"assetsByChunkName":{"app":["webpack-runtime-e54b03d4753e5c3fd11f.js","commons-811063c764ce48470d97.js","styles.56c03e9eefc5b509dfdc.css","styles-57426c4aa88004c8f7a1.js","app-1903c4c28ed1d0f1ff3b.js"],"component---src-templates-docs-js":[]}}