{"errors":[],"warnings":[],"namedChunkGroups":{"app":{"chunks":[3,2,1,0],"assets":["webpack-runtime-e54b03d4753e5c3fd11f.js","webpack-runtime-e54b03d4753e5c3fd11f.js.map","styles.e2e0dd898b1f6d402d5b.css","styles-8d90d931dfa2d1f3f813.js","styles-8d90d931dfa2d1f3f813.js.map","commons-715ebae7409f64c391a7.js","commons-715ebae7409f64c391a7.js.map","app-f959e798e963dac5e883.js","app-f959e798e963dac5e883.js.map"],"children":{},"childAssets":{}},"component---src-templates-docs-js":{"chunks":[],"assets":[],"children":{},"childAssets":{}}},"assetsByChunkName":{"app":["webpack-runtime-e54b03d4753e5c3fd11f.js","styles.e2e0dd898b1f6d402d5b.css","styles-8d90d931dfa2d1f3f813.js","commons-715ebae7409f64c391a7.js","app-f959e798e963dac5e883.js"],"component---src-templates-docs-js":[]}}